Workbook

Sheet Core_Assumptions
A1: Variable | B1: Value | C1: Justification
A2: Currency | B2: CAD | C2: Model in Canadian dollars
A3: Monthly ARPU Y1-Y5 | B3: 244,259,274,287,299 | C3: Plan mix shifts toward Professional and Enterprise
A4: Monthly churn Y1-Y5 | B4: 1.8%,1.6%,1.4%,1.4%,1.4% | C4: Retention improves with workflow embedding
A5: Avg providers per clinic | B5: 4.2 | C5: Small-medium outpatient clinic target
A6: COGS per provider per month | B6: 54 | C6: Inference + hosting + storage + support + fees
A7: Implementation fee per new clinic Y1-Y5 | B7: 1500,1500,2000,2000,2000 | C7: Onboarding and training
A8: Capex Y1-Y5 | B8: 180000,220000,280000,350000,420000 | C8: Security and platform scaling
A9: Initial cash | B9: 200000 | C9: Founder and pre-seed cash
A10: Financing Y1-Y5 | B10: 1500000,1800000,2000000,0,0 | C10: Fundraise plan to break-even

Sheet Growth_Pricing
A1: Year | B1: Clinics_EOY | C1: Providers_EOY | D1: Providers_Avg | E1: Basic_Mix | F1: Pro_Mix | G1: Ent_Mix | H1: Basic_Price | I1: Pro_Price | J1: Ent_Price | K1: Blended_ARPU | L1: Sub_Revenue | M1: Impl_Fee | N1: Impl_Revenue | O1: Total_Revenue
A2: Y1 | B2: 22 | C2: 90 | D2: 70 | E2: 0.6 | F2: 0.35 | G2: 0.05 | H2: 199 | I2: 299 | J2: 399 | K2: =E2*H2+F2*I2+G2*J2 | L2: =D2*K2*12 | M2: 1500 | N2: =B2*M2 | O2: =L2+N2
A3: Y2 | B3: 76 | C3: 320 | D3: 260 | E3: 0.5 | F3: 0.4 | G3: 0.1 | H3: 199 | I3: 299 | J3: 399 | K3: =E3*H3+F3*I3+G3*J3 | L3: =D3*K3*12 | M3: 1500 | N3: =B3*M3 | O3: =L3+N3
A4: Y3 | B4: 214 | C4: 900 | D4: 760 | E4: 0.4 | F4: 0.45 | G4: 0.15 | H4: 199 | I4: 299 | J4: 399 | K4: =E4*H4+F4*I4+G4*J4 | L4: =D4*K4*12 | M4: 2000 | N4: =B4*M4 | O4: =L4+N4
A5: Y4 | B5: 500 | C5: 2100 | D5: 1850 | E5: 0.32 | F5: 0.48 | G5: 0.2 | H5: 199 | I5: 299 | J5: 399 | K5: =E5*H5+F5*I5+G5*J5 | L5: =D5*K5*12 | M5: 2000 | N5: =B5*M5 | O5: =L5+N5
A6: Y5 | B6: 980 | C6: 4200 | D6: 3700 | E6: 0.25 | F6: 0.5 | G6: 0.25 | H6: 199 | I6: 299 | J6: 399 | K6: =E6*H6+F6*I6+G6*J6 | L6: =D6*K6*12 | M6: 2000 | N6: =B6*M6 | O6: =L6+N6

Sheet COGS
A1: Component | B1: Cost_per_provider_per_month
A2: LLM inference + summarization | B2: 24
A3: Cloud hosting + networking | B3: 11
A4: Storage + logging | B4: 5
A5: Support + implementation servicing | B5: 8
A6: Payment processing + marketplace fees | B6: 6
A7: Total COGS per provider/month | B7: =SUM(B2:B6)
A9: Year | B9: Avg_Providers | C9: Revenue | D9: COGS | E9: Gross_Profit | F9: Gross_Margin
A10: Y1 | B10: =Growth_Pricing!D2 | C10: =Growth_Pricing!O2 | D10: =B10*$B$7*12 | E10: =C10-D10 | F10: =E10/C10
A11: Y2 | B11: =Growth_Pricing!D3 | C11: =Growth_Pricing!O3 | D11: =B11*$B$7*12 | E11: =C11-D11 | F11: =E11/C11
A12: Y3 | B12: =Growth_Pricing!D4 | C12: =Growth_Pricing!O4 | D12: =B12*$B$7*12 | E12: =C12-D12 | F12: =E12/C12
A13: Y4 | B13: =Growth_Pricing!D5 | C13: =Growth_Pricing!O5 | D13: =B13*$B$7*12 | E13: =C13-D13 | F13: =E13/C13
A14: Y5 | B14: =Growth_Pricing!D6 | C14: =Growth_Pricing!O6 | D14: =B14*$B$7*12 | E14: =C14-D14 | F14: =E14/C14

Sheet Hiring
A1: Role | B1: Salary | C1: Y1 | D1: Y2 | E1: Y3 | F1: Y4 | G1: Y5 | H1: Year5_Annual_Cost
A2: Leadership/Ops | B2: 180000 | C2: 2 | D2: 2 | E2: 2 | F2: 2 | G2: 2 | H2: =B2*G2
A3: Backend/Platform Engineer | B3: 135000 | C3: 2 | D3: 2 | E3: 5 | F3: 6 | G3: 7 | H3: =B3*G3
A4: ML Engineer | B4: 145000 | C4: 1 | D4: 2 | E4: 3 | F4: 3 | G4: 4 | H4: =B4*G4
A5: Clinical AI Specialist | B5: 125000 | C5: 1 | D5: 1 | E5: 1 | F5: 2 | G5: 2 | H5: =B5*G5
A6: Product Manager | B6: 140000 | C6: 0 | D6: 1 | E6: 1 | F6: 2 | G6: 3 | H6: =B6*G6
A7: Compliance/Privacy Officer | B7: 120000 | C7: 0 | D7: 1 | E7: 1 | F7: 1 | G7: 2 | H7: =B7*G7
A8: Sales/Partnerships (OTE) | B8: 130000 | C8: 0 | D8: 0 | E8: 1 | F8: 3 | G8: 6 | H8: =B8*G8
A9: Customer Success/Implementation | B9: 95000 | C9: 0 | D9: 1 | E9: 2 | F9: 5 | G9: 7 | H9: =B9*G9
A11: Metric | B11: Y1 | C11: Y2 | D11: Y3 | E11: Y4 | F11: Y5
A12: Total FTE | B12: =SUM(C2:C9) | C12: =SUM(D2:D9) | D12: =SUM(E2:E9) | E12: =SUM(F2:F9) | F12: =SUM(G2:G9)
A13: Base Payroll | B13: =SUMPRODUCT(B2:B9,C2:C9) | C13: =SUMPRODUCT(B2:B9,D2:D9) | D13: =SUMPRODUCT(B2:B9,E2:E9) | E13: =SUMPRODUCT(B2:B9,F2:F9) | F13: =SUMPRODUCT(B2:B9,G2:G9)
A14: Payroll w/18% burden | B14: =B12*1.18 | C14: =C12*1.18 | D14: =D12*1.18 | E14: =E12*1.18 | F14: =F12*1.18

Sheet Opex
A1: Category | B1: Y1 | C1: Y2 | D1: Y3 | E1: Y4 | F1: Y5
A2: Marketing and demand generation | B2: 180000 | C2: 320000 | D2: 700000 | E2: 1400000 | F2: 2700000
A3: Legal and compliance | B3: 60000 | C3: 80000 | D3: 110000 | E3: 170000 | F3: 250000
A4: Conferences and travel | B4: 20000 | C4: 40000 | D4: 70000 | E4: 120000 | F4: 180000
A5: SaaS tools and software ops | B5: 45000 | C5: 65000 | D5: 95000 | E5: 140000 | F5: 190000
A6: Infrastructure overhead (non-COGS) | B6: 40000 | C6: 55000 | D6: 85000 | E6: 130000 | F6: 180000
A7: Insurance and admin overhead | B7: 23000 | C7: 30000 | D7: 45000 | E7: 70000 | F7: 95000
A8: Total non-payroll Opex | B8: =SUM(B2:B7) | C8: =SUM(C2:C7) | D8: =SUM(D2:D7) | E8: =SUM(E2:E7) | F8: =SUM(F2:F7)

Sheet Financials
A1: Metric | B1: Y1 | C1: Y2 | D1: Y3 | E1: Y4 | F1: Y5
A2: Revenue | B2: =Growth_Pricing!O2 | C2: =Growth_Pricing!O3 | D2: =Growth_Pricing!O4 | E2: =Growth_Pricing!O5 | F2: =Growth_Pricing!O6
A3: COGS | B3: =COGS!D10 | C3: =COGS!D11 | D3: =COGS!D12 | E3: =COGS!D13 | F3: =COGS!D14
A4: Gross Profit | B4: =B2-B3 | C4: =C2-C3 | D4: =D2-D3 | E4: =E2-E3 | F4: =F2-F3
A5: Payroll SG&A | B5: =Hiring!B13 | C5: =Hiring!C13 | D5: =Hiring!D13 | E5: =Hiring!E13 | F5: =Hiring!F13
A6: Non-Payroll Opex | B6: =Opex!B8 | C6: =Opex!C8 | D6: =Opex!D8 | E6: =Opex!E8 | F6: =Opex!F8
A7: Total SG&A | B7: =B5+B6 | C7: =C5+C6 | D7: =D5+D6 | E7: =E5+E6 | F7: =F5+F6
A8: EBITDA | B8: =B4-B7 | C8: =C4-C7 | D8: =D4-D7 | E8: =E4-E7 | F8: =F4-F7
A9: EBITDA Margin | B9: =B8/B2 | C9: =C8/C2 | D9: =D8/D2 | E9: =E8/E2 | F9: =F8/F2
A10: Capex | B10: 180000 | C10: 220000 | D10: 280000 | E10: 350000 | F10: 420000
A11: Net Cash Flow pre-financing | B11: =B8-B10 | C11: =C8-C10 | D11: =D8-D10 | E11: =E8-E10 | F11: =F8-F10
A12: Financing | B12: 1500000 | C12: 1800000 | D12: 2000000 | E12: 0 | F12: 0
A13: Ending Cash | B13: =200000+B11+B12 | C13: =B13+C11+C12 | D13: =C13+D11+D12 | E13: =D13+E11+E12 | F13: =E13+F11+F12

Sheet CAC_Payback
A1: Year | B1: New Providers | C1: Sales+Marketing Spend | D1: CAC per Provider | E1: ARPU | F1: Monthly GP/Provider | G1: Payback Months
A2: Y1 | B2: 90 | C2: =Opex!B2 | D2: =C2/B2 | E2: =Growth_Pricing!K2 | F2: =E2-COGS!$B$7 | G2: =D2/F2
A3: Y2 | B3: 230 | C3: =Opex!C2 | D3: =C3/B3 | E3: =Growth_Pricing!K3 | F3: =E3-COGS!$B$7 | G3: =D3/F3
A4: Y3 | B4: 580 | C4: =Opex!D2 | D4: =C4/B4 | E4: =Growth_Pricing!K4 | F4: =E4-COGS!$B$7 | G4: =D4/F4
A5: Y4 | B5: 1200 | C5: =Opex!E2 | D5: =C5/B5 | E5: =Growth_Pricing!K5 | F5: =E5-COGS!$B$7 | G5: =D5/F5
A6: Y5 | B6: 2100 | C6: =Opex!F2 | D6: =C6/B6 | E6: =Growth_Pricing!K6 | F6: =E6-COGS!$B$7 | G6: =D6/F6

Sheet SmartHelping_Mapping
A1: Template Section | B1: Model Input / Formula Source
A2: Monthly price / ARPU assumptions | B2: Growth_Pricing!K2:K6
A3: Subscriber growth assumptions | B3: Growth_Pricing!D2:D6
A4: New subscribers | B4: CAC_Payback!B2:B6
A5: Monthly churn | B5: Core_Assumptions!B4
A6: COGS per subscriber | B6: COGS!B7
A7: Marketing spend | B7: Opex!B2:F2
A8: Payroll assumptions | B8: Hiring!A2:G9 and Hiring!B13:F13
A9: Other SG&A | B9: Opex!B8:F8
A10: Revenue | B10: Financials!B2:F2
A11: Gross margin | B11: COGS!F10:F14
A12: EBITDA | B12: Financials!B8:F8
A13: Cash flow and cash balance | B13: Financials!B11:F13
